guolei_py3_wisharetec/__init__.py
guolei_py3_wisharetec/scaasp.py
guolei_py3_wisharetec/library/__init__.py
guolei_py3_wisharetec/library/scaasp/__init__.py
guolei_py3_wisharetec/library/scaasp/admin/__init__.py
guolei_py3_wisharetec/library/scaasp/admin/api.py
guolei_py3_wisharetec-2.3.2.dist-info/licenses/LICENSE
guolei_py3_wisharetec-2.3.2.dist-info/METADATA
guolei_py3_wisharetec-2.3.2.dist-info/WHEEL
guolei_py3_wisharetec-2.3.2.dist-info/top_level.txt
guolei_py3_wisharetec-2.3.2.dist-info/RECORD
