Metadata-Version: 2.4
Name: guolei-py3-wisharetec
Version: 2.3.2
Summary: 慧享(绿城)科技 API
Home-page: https://github.com/guolei19850528/guolei_py3_wisharetec
Author: guolei
Author-email: 174000902@qq.com
License: MIT
Requires-Python: >=3.0
License-File: LICENSE
Requires-Dist: guolei-py3-requests
Requires-Dist: requests
Requires-Dist: diskcache
Requires-Dist: redis
Requires-Dist: addict
Requires-Dist: retrying
Requires-Dist: jsonschema
Dynamic: author
Dynamic: author-email
Dynamic: description
Dynamic: description-content-type
Dynamic: home-page
Dynamic: license
Dynamic: license-file
Dynamic: requires-dist
Dynamic: requires-python
Dynamic: summary
